r3make/__init__.py
r3make/cli.py
r3make/core.py
r3make/util.py
r3make/version.py
r3make/cmd/clangdcmd.py
r3make/cmd/gitdeps.py
r3make-2025.2.8.dist-info/licenses/LICENSE
r3make-2025.2.8.dist-info/METADATA
r3make-2025.2.8.dist-info/WHEEL
r3make-2025.2.8.dist-info/entry_points.txt
r3make-2025.2.8.dist-info/top_level.txt
r3make-2025.2.8.dist-info/RECORD
