Metadata-Version: 2.4
Name: r3make
Version: 2025.2.8
Summary: Simple JSON-based CLI build tool for C!!!
Author: r3shape
License: MIT
Keywords: cli,c,build,compiler,json,tool
Requires-Python: >=3.8
License-File: LICENSE
Dynamic: license-file
